{"location": "./dcfg\\com.flaps.herbfun\\0e4ab90620826e04", "block": ["[TAG: goto_0 - (line 778)]\n"], "real_child_block": ["[TAG: goto_0 - (line 778)]\n"], "emu_child_blocks": [["[TAG: True:cond_0 - (line 798)]\n", "[Method END]\n"]]}
{"location": "./dcfg\\com.flaps.herbfun\\204d9a3022588076", "block": ["[TAG: goto_0 - (line 87)]\n", "[Branch: if-ge v1, v0, :cond_2 - (line 88)]\n", "[Branch: if-eq v4, v5, :cond_1 - (line 106)]\n"], "real_child_block": ["[TAG: False:cond_1 - (line 106)]\n", "[Branch: if-ge v0, v1, :cond_0 - (line 112)]\n"], "emu_child_blocks": [["[TAG: True:cond_1 - (line 123)]\n"]]}
{"location": "./dcfg\\com.flaps.herbfun\\2def8e1730f66a1a", "block": ["[Branch: if-nez v13, :cond_0 - (line 286)]\n"], "real_child_block": ["[TAG: False:cond_0 - (line 286)]\n", "[Method END]\n"], "emu_child_blocks": [["[TAG: True:cond_0 - (line 292)]\n", "[Method END]\n"]]}
{"location": "./dcfg\\com.flaps.herbfun\\6adbe9b12a7f5d24", "block": ["[Branch: if-ne v0, v1, :cond_6 - (line 1987)]\n"], "real_child_block": ["[TAG: False:cond_7 - (line 1973)]\n"], "emu_child_blocks": [["[TAG: True:cond_6 - (line 2009)]\n"]]}
{"location": "./dcfg\\com.flaps.herbfun\\89fbe009d0cbd135", "block": ["[TAG: try_start_4 - (line 902)]\n"], "real_child_block": ["[TAG: try_end_0->:catch_0 - (line 869)]\n"], "emu_child_blocks": [["[TAG: try_end_4->:catch_0 - (line 915)]\n", "[Branch: if-eqz p1, :cond_2 - (line 918)]\n"]]}
{"location": "./dcfg\\com.flaps.herbfun\\a3a00ed2d36bc3d3", "block": ["[TAG: try_start_a - (line 545)]\n"], "real_child_block": ["[TAG: try_end_8->:catch_1 - (line 516)]\n"], "emu_child_blocks": [["[TAG: try_end_a->:catch_1 - (line 573)]\n", "[Branch: if-eqz v16, :cond_3 - (line 577)]\n"], ["[TAG: try_end_d->:catch_1 - (line 634)]\n"]]}
{"location": "./dcfg\\com.flaps.herbfun\\a3a00ed2d36bc3d3", "block": ["[TAG: False:cond_1 - (line 612)]\n"], "real_child_block": ["[TAG: True:cond_1,try_start_e - (line 640)]\n"], "emu_child_blocks": [["[TAG: try_start_c - (line 614)]\n"]]}
